Metadata-Version: 2.1
Name: stb-utils
Version: 1.0.1
Summary: Common utility functions for stabila codebases.
Home-page: https://github.com/stabilaclick/stabila-utils
Author: Moneta Stabila
Author-email: monetasatbila@gmail.com
License: MIT
Platform: UNKNOWN
Classifier: Intended Audience :: Developers
Classifier: License :: OSI Approved :: MIT License
Classifier: Natural Language :: English
Classifier: Programming Language :: Python :: 3
Classifier: Programming Language :: Python :: 3.6
Classifier: Programming Language :: Python :: 3.7
Requires-Python: >=3.5,!=3.5.2,<4
